{
    "title": "500 миллионов бегумы",
    "author": "Верн",
    "annotation": "На наследство индийской принцессы в Америке возводятся два города — идеальный и военизированный. Правитель военизированного города хочет уничтожить ненавистного соседа, создаёт ужасное оружие, но из-за собственной ошибки губит свой город. Марсель и Октав отправляются в город, чтобы узнать, что случилось с Шульцем. Они обнаруживают его мертвым и узнают, что он разработал снаряд, который должен был распылять яд, не повреждая зданий. Однако из-за ошибки Шульца яд распространился по всему городу, убив всех его жителей.",
    "categories": [
        "Верн, Жюль",
        "Романы",
        "Все пересказы по алфавиту",
        "Слишком длинные микропересказы"
    ],
    "source_file": "d772af13e3e7be86434673ec68c2c47bc14f5d20733c456c8fe74bdd77eab028.raw",
    "unprocessed_annotation": "романа\nМикропересказ\n:\n \nНа наследство индийской принцессы в Америке возводятся два города — идеальный и военизированный. Правитель военизированного города хочет уничтожить ненавистного соседа, создаёт ужасное оружие, но из-за собственной ошибки губит свой город.\n\n\nЭтот микропересказ слишком длинный: 238 зн. Оптимальный размер: 190—200 знаков.\n\n\n\n\nПятьсот миллионов — это наследство индийской принцессы (бегумы), которое ждёт своего наследника. Оно переходит французскому врачу Сарассину, который непомерно счастлив. Он намеревается на эти деньги построить современный, чистый и развивающийся город. Но немецкий учёный, профессор Шульц, претендует на наследство и тоже хочет построить город. Его представления о нём отличаются от идеи Сарассина. Шульц мечтает о стальной, оружейной империи, в которой будет много орудий и пушек.\n\nОба плана претворяются в жизнь. Напротив военизированного Штальштадта возникает чистый и идеальный город Франсевиль. Вскоре между двумя городами разгорается конфликт. Шульц нацеливает свои пушки с непонятными снарядами на конкурентов.\n\nМолодой эльзасский инженер Марсель Брукманн проникает под чужой фамилией в город и входит в доверие к Шульцу. Строитель огромной пушки и тайного оружия никого не подпускает к своему изобретению. Брукману удаётся бежать и предупредить об ужасных планах жителей Франсвиля. В последний момент Марсель обнаруживает ошибку в расчётах Щульца. Выстрел, как и полагал Марсель, не попадает в цель.\n\nВ Стальном городе воцаряется тишина. Ходят слухи, что Шульце обанкротился. Город больше не подаёт признаков жизни. Марсель вместе с Окатавом, сыном Сарассина, отправляются в город, чтобы решить эту загадку. Они обнаруживают Шульца мёртвым и выясняют, что он разработал снаряд, который не принесёт вреда зданиям, но распылит над объектом яд. из-за ошибки изобретателя погиб весь город."
}