{
    "title": "«Архимед» Вовки Грушина",
    "author": "Сотник",
    "annotation": "Закадычные друзья Серёжка, Андрюшка и Галка готовились к экзаменам. Подготовку прервал Вовка Грушин, пришедший за плоскогубцами.\n\nВовка Грушин  — юный техник-изобретатель, забросивший из-за изобретений учёбу.\n\nВовка что-то изобрёл, но рассказывать не хотел, это тайна. Из-за своего изобретения он уже провалил два экзамена и отказался от поездки в лагерь, но будет жить на даче, которая находится рядом с лагерем.\n\nРебята уехали в лагерь. Там они из двух лодок сделали крейсеры и устроили на речке морской бой. Во время игры они случайно сбили с плота оказавшегося рядом Вовку. Пионервожатая возмутилась, почему Вовка отделился от ребят. Ребята решили найти его и пришли к нему на дачу. Оказалось, что Вовка говорил матери, что идёт к ребятам в лагерь, а сам тайно работал над своим изобретением.\n\nВовка прислал друзьям, Андрюшке, Серёжке и Галке, записку, в которой просил помочь тайком уйти ночью из лагеря и встретиться в назначенном месте. Ребята оказались в раздумьях.\n\nУдрать из лагеря ночью — за такое дело можно вылететь из отряда. Выдать Вовкину тайну было бы не по-товарищески.\n\nРебята без спроса ночью пришли в указанное место. Вовка уже когда-то изобрёл ракетный двигатель, из-за чего произошёл несчастный случай. На этот раз Вовка изобрёл подводную лодку, которую назвал «Архимед». Он попросил друзей помочь завинтить за ним люк и погрузился на дно реки. Вскоре лодка глубоко увязла в иле и в люк начала просачиваться вода.\n\nРебята были вынуждены обратиться за помощью. Вовку привезли в лагерь и отпоили горячими чаем. Один из ребят спросил, что такое «Архимед», не рыба ли? Вовка презрительно ответил, что это полководец.",
    "categories": [
        "Сотник, Юрий Вячеславович",
        "Рассказы",
        "Все пересказы по алфавиту"
    ],
    "source_file": "b9ac5e6ce550006abaf5b5330e2b27c4b82a4c752ab87335a0ed5f5f3bb19d87.raw",
    "unprocessed_annotation": "рассказа\nМикропересказ\n:\n \nЮный техник-изобретатель, жертвуя учёбой и отдыхом, втайне от друзей, изобрёл подводную лодку, но при её испытании происходит авария, ему пришлось попросить о помощи и об изобретении узнают все.\n\n\n\n\nЗакадычные друзья Серёжка, Андрюшка и Галка готовились к экзаменам. Подготовку прервал Вовка Грушин, пришедший за плоскогубцами.\n\n\n\n\n\n 👤 \n\n\nВовка Грушин\n — юный техник-изобретатель, забросивший из-за изобретений учёбу.\n\n\nВовка что-то изобрёл, но рассказывать не хотел, это тайна. Из-за своего изобретения он уже провалил два экзамена и отказался от поездки в лагерь, но будет жить на даче, которая находится рядом с лагерем.\n\nРебята уехали в лагерь. Там они из двух лодок сделали крейсера и устроили на речке морской бой. Во время игры они случайно сбили с плота оказавшегося рядом Вовку. Пионервожатая возмутилась, почему Вовка отделился от ребят. Ребята решили найти его и пришли к нему на дачу. Оказалось, что Вовка говорил матери, что идёт к ребятам в лагерь, а сам тайно работал над своим изобретением.\n\nВовка прислал друзьям, Андрюшке, Серёжке и Галке, записку, в которой просил помочь тайком уйти ночью из лагеря и встретиться в назначенном месте. Ребята оказались в раздумьях.\n\n\n\n\n\nУдрать из лагеря ночью — за такое дело можно вылететь из отряда. Выдать Вовкину тайну было бы не по-товарищески.\n\n\n\n\n\nРебята без спроса ночью пришли в указанное место. Вовка уже когда-то изобрёл ракетный двигатель, из-за чего произошёл несчастный случай. На этот раз Вовка изобрёл подводную лодку, которую назвал «Архимед». Он попросил друзей помочь завинтить за ним люк и погрузился на дно реки. Вскоре лодка глубоко увязла в иле и в люк начала просачиваться вода.\n\nРебята были вынуждены обратиться за помощью. Вовку привезли в лагерь и отпоили горячими чаем. Один из ребят спросил, что такое «Архимед», не рыба ли? Вовка презрительно ответил, что это полководец.\n\nЗа основу пересказа взято Государственное издание детской литературы Министерства Просвещения РСФСР, Москва 1958 год."
}