{
    "title": "Бэзил",
    "author": "Коллинз",
    "annotation": "Бэзил, чей отец блюдёт семейные ценности и не разрешает сыну жениться без его на то дозволения, влюбляется с первого взгляда в девушку, которую увидел в омнибусе. Он следует за ней и узнаёт, что зовут её Маргарет Шьюрин, и она является дочерью драпировщика по льну. Бэзил убеждает её отца тайно выдать за него Маргарет. Отец соглашается, но при условии, что первый год они будут жить раздельно.\n\nПо началу всё идёт по плану, пока таинственный Маннион, чьи эмоции нельзя прочитать на лице, не возвращается из-за границы. В предновогоднюю ночь Бэзил следит за Маргарет и Мэннионом и застаёт их «в деликатном положении». Бэзил нападает на Мэнниона на улице и пытается убить его, но ему удаётся только изуродовать ему лицо, ударив его о гудронированное шоссе. Мэннион выживает, оправляется и жаждет мести.\n\nВскоре выясняется, что отец Бэзила косвенно обвинил отца Мэнниона в подлоге.\n\nБэзил отказывается от Маргарет, но она угрожает ему разоблачением, пока он не разведён. Бэзил признаётся во всём своему отцу, который отрекается от него, но сестра Клара на его стороне. Брат Бэзила Ральф предлагает откупиться от Шьюрин, в то время как Маргарет бежит к Мэнниону, тем самым признавая свою вину. Посещая Мэнниона в госпитале, она заражается тифом и умирает. Бэзил навещает её на смертном одре, а затем уезжает в Корнуолл.",
    "categories": [
        "Коллинз, Уилки",
        "Романы",
        "Все пересказы по алфавиту",
        "Слишком короткие пересказы",
        "Слишком короткие микропересказы"
    ],
    "source_file": "fec063759ae895262d5e93274ef910c12a3a62c0c24e34bda7d0e869cd7dade9.raw",
    "unprocessed_annotation": "романа\nМикропересказ\n:\n \nЧеловек из высшего общества влюблён в красавицу. Он обнаруживает, что стал жертвой зловещего плана мести, выслеживает своего мучителя и в жестокой схватке решает свою судьбу…\n\n\nЭтот микропересказ слишком короткий: 174 зн. Оптимальный размер: 190—200 знаков.\n\n\n\n\nБэзил, чей отец блюдёт семейные ценности и не разрешает сыну жениться без его на то дозволения, влюбляется с первого взгляда в девушку, которую увидел в омнибусе. Он следует за ней и узнаёт, что зовут её Маргарет Шьюрин, и она является дочерью драпировщика по льну. Бэзил убеждает её отца тайно выдать за него Маргарет. Отец соглашается, но при условии, что первый год они будут жить раздельно.\n\nПо началу всё идёт по плану, пока таинственный Маннион, чьи эмоции нельзя прочитать на лице, не возвращается из-за границы. В предновогоднюю ночь Бэзил следит за Маргарет и Мэннионом и застаёт их «в деликатном положении». Бэзил нападает на Мэнниона на улице и пытается убить его, но ему удаётся только изуродовать ему лицо, ударив его о гудронированное шоссе. Мэннион выживает, оправляется и жаждет мести.\n\nВскоре выясняется, что отец Бэзила косвенно обвинил отца Мэнниона в подлоге.\n\nБэзил отказывается от Маргарет, но она угрожает ему разоблачением, пока он не разведён. Бэзил признаётся во всём своему отцу, который отрекается от него, но сестра Клара на его стороне. Брат Бэзила Ральф предлагает откупиться от Шьюрин, в то время как Маргарет бежит к Мэнниону, тем самым признавая свою вину. Посещая Мэнниона в госпитале, она заражается тифом и умирает. Бэзил навещает её на смертном одре, а затем уезжает в Корнуолл."
}