{
    "title": "В потопе времени",
    "author": "Олдисс",
    "annotation": "Далёкое будущее. В высокоразвитом техногенном обществе проводятся эксперименты со временем. Фифи Фивертри с помощью хроногаза удаляют зуб и выращивают новый. На аэрокэбе она возвращается в загородный элитный поселок Роузвилл, куда только что провели хронопровод. За городом жить дороже, но правительство платит за это компенсацию. А город находится под раздвижным защитным куполом.\n\nНесколько месяцев в посёлке налаживали хронопровод с хроногазом из Хроноцентраля. В каждом доме на кухне установили панель времени рядом с пультом ядерного реактора. К моменту возвращения Фифи выявляются неполадки с давлением хроногаза, но подрядчик обещает устранить их в кратчайшие сроки. Население с нетерпением ждёт запуска новой игрушки.\n\nФифи с мужем Трейси экспериментируют с хроногазом, переносясь в разные периоды жизни, в основном в недавнее прошлое. Эта игра забавляет их.\n\nМы могли бы вернуться в то время, когда оба были малышами! Только нужно быть осторожным, чтобы ненароком не унестись дальше дня своего рождения…\n\nДля хронопроводов Роузвилла существует предел — человек может перенестись в сознание своих бабушек и дедушек, но не дальше.\n\nСупруги ужинают синтетической едой и вдруг чувствуют, что с хронопроводом творится неладное. Время идёт бешеным ритмом, а супруги сидят за столом, где появляются и исчезают блюда. Звонок подрядчику проясняет ситуацию: «…в Роузвилле неполадки. Там, где (местная) линия отходит от магистрали. Хроногаз просачивается…».\n\nСупруги садятся в свой аппарат на воздушной подушке и летят над поселком к Хроноцентрали (раздатчику хроногаза). А время по-прежнему неустойчиво. Приземлившись, пара превращается в детей в телах взрослых. Когда идут к поселковой площади — они уже старики и еле тащатся. Оказавшись в посёлке, супруги понимают, что всё его население переживает «весь спектр возрастов — от лепечущего младенчества до стонущей дряхлости. Очевидно, на Хроноцентрали случилось что-то серьёзное».\n\nПодрядчик в противохроногазе объяснил, что строители наткнулись на твёрдый пласт ископаемого времени, которое разлилось во все стороны.\n\nЖители мысленно переносятся то во времена короля Георга III, то сухого закона, то маккартизма, то викингов. На площади слышен гвалт разновременных разговоров. Всё население решено эвакуировать.\n\nЭксперименты со временем начались около десяти лет назад, когда терронавты «наткнулись в толще земной коры на пласты ископаемого времени — хроногаза». Пока «наука пребывала в растерянности», промышленники вложили в хронопромыщленность большие средства и позаботились, «чтобы каждый — за плату — мог получить свою дозу времени». Хроноцентрали были проведение даже в крошечные посёлки вроде Роузвилла. И вот теперь роузвиллская хроноцентраль вышла из строя.\n\nФифи и Трейси мечутся во временах, не подозревая, что последовательность времени на планете нарушена и «губительный фонтан хроногаза затопил уже весь материк» и одурманенные люди проваливаются «всё дальше сквозь поколения, словно в бездонный омут».\n\nТерронавты — исследователи земных пластов — поднимаются наверх из разлома, где произошла авария, и рассказывают, что видели далёкое прошлое: динозавров и почти что сотворение мира. Невидимый фонтан времени бьёт из земли, унося одичавшее население далеко назад в первобытные времена.\n\nВместе с соседями Фифи и Трейси уходят из поселка, где ничего не понятно их примитивному уму, и выражают свои мысли нечленораздельным мычанием, которое можно трактовать как: «И почему такое случается с человечеством как раз тогда, когда оно уже готово вновь стать цивилизованным?».",
    "categories": [
        "Олдисс, Брайан Уилсон",
        "Рассказы",
        "Все пересказы по алфавиту",
        "Слишком короткие микропересказы"
    ],
    "source_file": "0acc4ce19466026f7f85ebc8a2d5a746f40cdf33ed9314f6b0dbe4c3e6ef800f.raw",
    "unprocessed_annotation": "рассказа\nМикропересказ\n:\n \nТехногенная катастрофа с хроногазом грозит отбросить человечество назад в прошлое.\n\n\nЭтот микропересказ слишком короткий: 82 зн. Оптимальный размер: 190—200 знаков.\n\n\n\n\nДалёкое будущее. В высокоразвитом техногенном обществе проводятся эксперименты со временем. Фифи Фивертри с помощью хроногаза удаляют зуб и выращивают новый. На аэрокэбе она возвращается в загородный элитный поселок Роузвилл, куда только что провели хронопровод. За городом жить дороже, но правительство платит за это компенсацию. А город находится под раздвижным защитным куполом.\n\nНесколько месяцев в посёлке налаживали хронопровод с хроногазом из Хроноцентраля. В каждом доме на кухне установили панель времени рядом с пультом ядерного реактора. К моменту возвращения Фифи выявляются неполадки с давлением хроногаза, но подрядчик обещает устранить их в кратчайшие сроки. Население с нетерпением ждёт запуска новой игрушки.\n\nФифи с мужем Трейси экспериментируют с хроногазом, переносясь в разные периоды жизни, в основном в недавнее прошлое. Эта игра забавляет их.\n\n\n\n\n\nМы могли бы вернуться в то время, когда оба были малышами! Только нужно быть осторожным, чтобы ненароком не унестись дальше дня своего рождения…\n\n\n\n\n\nДля хронопроводов Роузвилла существует предел — человек может перенестись в сознание своих бабушек и дедушек, но не дальше.\n\nСупруги ужинают синтетической едой и вдруг чувствуют, что с хронопроводом творится неладное. Время несётся бешеным ритмом, а супруги как заворожённые сидят за столом, гле появляются и исчезают блюда. Звонок подрядчику проясняет ситуацию: «…в Роузвилле неполадки. Там, где (местная) линия отходит от магистрали. Хроногаз просачивается…».\n\nСупруги садятся в свой аппарат на воздушной подушке и летят над поселком к Хроноцентрали (раздатчику хроногаза). А время по-прежнему неустойчиво. Приземлившись, пара превращается в детей в телах взрослых. Когда идут к поселковой площади — они уже старики и еле тащатся. Оказавшись в посёлке, супруги понимают, что всё его население переживает «весь спектр возрастов — от лепечущего младенчества до стонущей дряхлости. Очевидно, на Хроноцентрали случилось что-то серьёзное».\n\nПодрядчик в противохроногазе объяснил, что строители наткнулись на твёрдый пласт ископаемого времени, которое разлилось во все стороны.\n\n\n\n\n\n…невидимый фонтан ископаемого времени вздымается сейчас над поселком, и оно разливается во все стороны, неся в своих неистребимых струях позабытую память давно ушедших времен…\n\n\n\n\n\nЖители мысленно переносятся то во времена короля Георга III, то сухого закона, то маккартизма, то викингов. На площади слышен гвалт разновременных разговоров. Всё население решено эвакуировать.\n\nЭксперименты со временем начались около десяти лет назад, когда терронавты «наткнулись в толще земной коры на пласты ископаемого времени — хроногаза». Пока «наука пребывала в растерянности», промышленники вложили в хронопромыщленность большие средства и позаботились, «чтобы каждый — за плату — мог получить свою дозу времени». Хроноцентрали были проведение даже в крошечные посёлки вроде Роузвилла. И вот теперь роузвиллская хроноцентраль вышла из строя.\n\nФифи и Трейси мечутся во временах, не подозревая, что последовательность времени на планете нарушена и «губительный фонтан хроногаза затопил уже весь материк» и одурманенные люди проваливаются «всё дальше сквозь поколения, словно в бездонный омут».\n\nТерронавты — исследователи земных пластов — поднимаются наверх из разлома, где произошла авария, и рассказывают, что видели далёкое прошлое: динозавров и почти что сотворение мира. Невидимый фонтан времени бьёт из земли, унося одичавшее население далеко назад в первобытные времена.\n\nВместе с соседями Фифи и Трейси уходят из поселка, где ничего не понятно их примитивному уму, и выражают свои мысли нечленораздельным мычанием, которое можно трактовать как: «И почему такое случается с человечеством как раз тогда, когда оно уже готово вновь стать цивилизованным?».\n\nЗа основу пересказа взят перевод З. А. Бобырь."
}