{
    "title": "В те последние мгновения",
    "author": "Нагибин",
    "annotation": "Старик рассказал о последних мгновениях жизни первого космонавта, который погиб, испытывая новый самолёт. По его словам, космонавт отказался спасаться без своего товарища, несмотря на его уговоры.\n\nИван Николаевич был убеждён, что знает всё о смерти Юрия Гагарина.\n\nИван Николаевич Чубарин — житель села Еремино, пенсионер, «всю сознательную жизнь проработал на шатурском торфе в негромких должностях».\n\nЮрий Гагарин — первый космонавт мира, простой и отважный.\n\nОт умершего брата Ивану Николаевичу досталась хорошая изба - Настя уступила ему дом и переехала работать в город.\n\nНастя — племянница Ивана Николаевича, официантка в столовой для космонавтов.\n\nИменно Настя была последней, кто видел Гагарина в то холодное мартовское утро, когда Гагарин с Серёгиным шли к самолёту.\n\nСерёгин — друг Гагарина, лётчик-испытатель, инженер-полковник.\n\nДевушка подбежала к лётчикам. В руке она держала голубой билетик — талон на обед с инициалами космонавта. Гагарин упрекнул девушку за то, что она легко одета, но для Насти этот клочок бумаги казался документом большой важности. Гагарин отшутился, а затем спросил про обед, сказав что они скоро вернутся. Официантка стояла на краю аэродромного поля и видела, как самолет взлетел и скрылся высоко в небе.\n\nЧто произошло дальше, известно лишь Ивану Николаевичу. По его словам, когда самолёт шёл на посадку, в его мотор попало неизвестное тело.\n\nСамолёт начал терять высоту. Полковник приказал Гагарину катапультироваться, но вскоре обнаружил, что тот сидит на месте и удерживает кнопку. Юра отказался выполнять приказ. Спастись они могли только вдвоём. Их диалог занял считанные мгновения. Серёгин убеждал Гагарина, что он не имеет права жертвовать собой, но Юра наотрез отказывался спасаться: «Приказ для нас обоих, один я не буду…» Полковник приводил последние доводы, но голос его вскоре оборвался.\n\nИван Николаевич замолк, вытирая слёзы. Рассказчику эта сцена показалась отдалённо знакомой. Он вспомнил рассказа Бунина об отце и сыне, замёрзшем у него на руках во время метели.\n\nЭтот старый одинокий человек говорит тоже о сыне, и… всякий раз, рассказывая эту вовсе не придуманную историю, он прощается со своим прекрасным, знаменитым, так несправедливо рано ушедшим сыном.",
    "categories": [
        "Нагибин, Юрий Маркович",
        "Рассказы",
        "Все пересказы по алфавиту"
    ],
    "source_file": "e30e8dc7463a28ecdbf52acfff640fc2d5b1034bfbe661226ae0e0831951b8da.raw",
    "unprocessed_annotation": "рассказа\nиз цикла «\nМаленькие рассказы о большой судьбе\n»\nОригинал читается за 6 минут\nМикропересказ\n:\n \nСтарик рассказал о последних мгновениях жизни первого космонавта, который погиб, испытывая новый самолёт. По его словам, космонавт отказался спасаться без своего товарища, несмотря на его уговоры.\n\n\n\n\nИван Николаевич был убеждён. что знает всё о смерти Юрия Гагарина.\n\n\n\n\n\n 👨🏼‍🦳 \n\n\nИван Николаевич Чубарин\n — житель села Еремино, пенсионер, «всю сознательную жизнь проработал на шатурском торфе в негромких должностях».\n\n\n\n\n 🧑🏻‍🚀 \n\n\nЮрий Гагарин\n — первый космонавт мира, простой и отважный.\n\n\nОт умершего брата Ивану Николаевичу досталась хорошая изба - Настя уступила ему дом и переехала работать в город.\n\n\n\n\n\n 👩🏻 \n\n\nНастя\n — племянница Ивана Николаевича, официантка в столовой для космонавтов.\n\n\nИменно Настя была последней, кто видел Гагарина в то холодное мартовское утро, когда Гагарин с Серёгиным шли к самолёту.\n\n\n\n\n\n 👱🏻‍♂️ \n\n\nСерёгин\n — друг Гагарина, лётчик-испытатель, инженер-полковник.\n\n\nДевушка подбежала к лётчикам. В руке она держала голубой билетик — талон на обед с инициалами космонавта. Гагарин упрекнул девушку за то, что она легко одета, но для Насти этот клочок бумаги казался документом большой важности. Гагарин отшутился, а затем спросил про обед, сказав что они скоро вернутся. Официантка стояла на краю аэродромного поля и видела, как самолет взлетел и скрылся высоко в небе.\n\nЧто произошло дальше, известно лишь Ивану Николаевичу. По его словам, когда самолёт шёл на посадку, в его мотор попало неизвестное тело.\n\nСамолёт начал терять высоту. Полковник приказал Гагарину катапультироваться, но вскоре обнаружил, что тот сидит на месте и удерживает кнопку. Юра отказался выполнять приказ. Спастись они могли только вдвоём. Их диалог занял считанные мгновения. Серёгин убеждал Гагарина, что он не имеет права жертвовать собой, но Юра наотрез отказывался спасаться: «Приказ для нас обоих, один я не буду…» Полковник приводил последние доводы, но голос его вскоре оборвался.\n\nИван Николаевич замолк, вытирая слёзы. Рассказчику эта сцена показалась отдалённо знакомой. Он вспомнил рассказа Бунина об отце и сыне, замёрзшем у него на руках во время метели.\n\n\n\n\n\n…этот старый одинокий человек говорит тоже о сыне, и… всякий раз, рассказывая эту вовсе не придуманную историю, он прощается со своим прекрасным, знаменитым, так несправедливо рано ушедшим сыном.\n\n\n\n\n\nЗа основу пересказа взято издание рассказа из сборника «\nМаленькие рассказы о большой судьбе\n» (М.: Советская Россия, 1976)."
}