{
    "title": "Заколдованный замок",
    "author": "Несбит",
    "annotation": "Дети на летних каникулах попадают в удивительные приключения. Забавное чудище, живущее в песочной яме, или кольцо, найденное в замке, исполняют любые их желания. Однако, получив желаемое, дети попадают в такие невероятные ситуации, из которых нелегко найти выход.\n\nТрое ребят, Джимми, Джеральд и Кэтти, играли одним прекрасным днём и нашли пещеру, из которой красная нить привела их к замку со спящей красавицей. Джимми поцеловал её в щёку, и она проснулась. Дети стали расспрашивать её о замке, мальчики не верили, что она настоящая принцесса. Затем она предложила пойти в замок и поесть, потому что все они были очень голодны. Они пришли в замок усталые и голодные, и принцесса велела им молчать и ждать её. Позже она принесла поднос с хлебом, сыром и водой, и дети поели. После трапезы принцесса решила похвастаться своими сокровищами. Пройдя по тёмному коридору, они очутились в маленькой пустой комнате, принцесса прошептала заклинание, и в комнате появились сокровища. Она показывала сокровища и рассказывала об этом детям. На полке стояли специальные украшения, которые могли сделать принцессу невидимой, но дети не верили, и она решила им это доказать. Джимми жульничал и не закрывал глаз, из-за этого принцесса не могла разрушить чары и была в ярости. На самом деле принцесса была ненастоящей, это была обычная девушка по имени Мейбл, которая играла Спящую красавицу, все эти сокровища были трюками, но её невидимость не была ложью, она действительно стала невидимой. Она велела детям спуститься в беседку на склоне холма и ждать её. Дети решили, что Мейбл поедет с ними домой, написали прощальную записку и уехали. В доме детей они поужинали и легли спать, а утром позавтракали и пошли к тёте Мейбл, чтобы рассказать правду. Тётя не поверила словам детей и велела им возвращаться домой, но дети решили остаться в беседке на склоне холма. Там Мэйбл призналась, что очень голодна, дети поняли, что воровать еду — это плохо, и решили заработать. Они отправились на ярмарку, чтобы показать фокусы. Джими был волшебником, который мог двигать предметы, но на самом деле невидимая Мейбл двигала их. На ярмарке Джеральд представился мальчиком из Индии и собрал большую толпу, чтобы выступить. В конце концов Мейбл удалось снять кольцо, и Джеральд надел его, чтобы удивить публику, а затем они отправились домой. Но Мэйбл пришла в голову мысль вернуться домой, и они отправились в особняк вместе с невидимым Джеральдом. Тётя Мейбл очень обрадовалась, увидев девочку, и пообещала больше никогда на неё не сердиться. Тем временем наступила ночь. Джеральд прогуливался по саду, когда увидел белую фигуру. Это было просто чудо, потому что фигурки в беседке, где постоянно сидели дети, оживали, это было сказочное место.\n\nЗатем Джеральд сделал своё дело, закрыл дверь в сокровищницу, повесил ключ и приготовился уходить. Но потом ему, как и любому человеку, захотелось есть, и он стал искать кухню. Но в одной из комнат он обнаружил грабителей. Он пытался помочь, но они украли много серебра.\n\nРанним утром Джеральд вернулся домой усталый и замёрзший. Экономка ругалась из-за грязных простыней, кольцо упало с пальца Джеральда, и он стал виден, но кольцо было потеряно. Потом дети собрались и с изумлением слушали Джеральда, потому что он рассказывал ночную сказку про разбойников и серебро, а потом он решил помочь Джонсону, это тот человек, который работает в этом замке, особняке, ну, он хотел рассказать, куда делись разбойники. С детьми и Джонсоном был полицейский.\n\nОни вернулись в детский дом и поужинали, а потом все принялись искать кольцо, и Мейбл обвинила их горничную в краже кольца. Горничная Лиз действительно надела кольцо и стала невидимой, она пошла встречать своего жениха, а он был просто в шоке, он думал, что заболел или сошел с ума. Лиз была очень расстроена, она плакала и не знала, что делать, дети пошли в беседку на пикник с Лиз.\n\nНаступил вечер, и служанка Лиз заметила, что статуи движутся. Вот что происходит, когда вы надеваете Волшебное кольцо-невидимку. Она дотронулась до статуэтки и очень испугалась, в результате все-таки сняла кольцо и пообещала больше никогда не носить чужие украшения.\n\nПотом они купили газету, в которой было написано имя Джонсона и его подвиги с грабителями. Потом ребята пошли на рынок и купили цветы для Мадмазель, они пришли домой и подарили ей цветы. Мадмазель начала приглашать Мейбл в замок, и та рассказала ей всю историю. Муадмозелю очень понравилась Мейбл, и она решила устроить небольшой праздничный ужин. Она купила много вкусных вещей, и дети устроили для нее представление. Это очень длинная история со спектаклем, очень длинная, и в конце спектакля все чучела животных ожили. Это все из-за кольца, оно стало странным.\n\nМуадмозель в панике выбежал из дома. Они успокоили муадмозеля и подумали о том, что делать с пугалами, как убрать колдовство. Мейбл и Джеральд отнесли мягкие игрушки в беседку и стали гадать, когда же кончится это волшебство. Кстати, эти пугала были очень воспитаны, разговаривали как настоящие джентльмены, читать было очень смешно. Тогда лесник увидел все это, запер чучела и попросил Джеральда рассказать ему, что случилось.\n\nОни рассказали Леснику всю историю с кольцом и договорились встретиться на следующий день в 10, но Лесник открыл дверь раньше, и мягкие игрушки ранили его. Дети нашли дровосека и помогли ему, но одно чучело все еще было живо. Они придумали план, как заманить его и снять с него пальто, но случилось ужасное. Джимми буквально рос у них на глазах, и в конце концов он стал похож на сорокалетнего старика. Дети плакали и не знали, что делать. В результате им удалось снять заклятие, и они решили спрятать кольцо в замке и не трогать его.",
    "categories": [
        "Пересказы без блочных цитат",
        "Несбит, Эдит",
        "Романы",
        "Все пересказы по алфавиту",
        "Слишком длинные микропересказы"
    ],
    "source_file": "dc591a3cbb35de33f82acfea8c9cfb324a6654aa4c3d9647ad3f0c983c09f072.raw",
    "unprocessed_annotation": "романа\nМикропересказ\n:\n \nДети на летних каникулах попадают в удивительные приключения. Забавное чудище, живущее в песочной яме, или кольцо, найденное в замке, исполняют любые их желания. Однако, получив желаемое, дети попадают в такие невероятные ситуации, из которых нелегко найти выход.\n\n\nЭтот микропересказ слишком длинный: 263 зн. Оптимальный размер: 190—200 знаков.\n\n\n\n\nТрое ребят, Джимми, Джеральд и Кэтти, играли одним прекрасным днём и нашли пещеру, из которой красная нить привела их к замку со спящей красавицей. Джимми поцеловал её в щёку, и она проснулась. Дети стали расспрашивать её о замке, мальчики не верили, что она настоящая принцесса. Затем она предложила пойти в замок и поесть, потому что все они были очень голодны.\n\nОни пришли в замок усталые и голодные, и принцесса велела им молчать и ждать её. Позже она принесла поднос с хлебом, сыром и водой, и дети поели. После трапезы принцесса решила похвастаться своими сокровищами. Пройдя по тёмному коридору, они очутились в маленькой пустой комнате, Принцесса прошептала заклинание, и в комнате появились сокровища.\n\nОна показывала сокровища и рассказывала об этом детям. На полке стояли специальные украшения, которые могли сделать принцессу невидимой, но дети не верили и она решила им это доказать. Джимми жульничал и не закрывал глаз, из-за этого принцесса не могла разрушить чары и была в ярости.\n\nНа самом деле принцесса была ненастоящей, это была обычная девушка по имени Мейбл, которая играла Спящую красавицу, все эти сокровища были трюками, но её невидимость не была ложью, она действительно стала невидимой. Она велела детям спуститься в беседку на склоне холма и ждать её.\n\nДети решили, что Мейбл поедет с ними домой, написали прощальную записку и уехали. В доме детей они поужинали и легли спать, а утром позавтракали и пошли к тёте Мейбл, чтобы рассказать правду. Тётя не поверила словам детей и велела им возвращаться домой, но дети решили остаться в беседке на склоне холма.\n\nТам Мэйбл призналась, что очень голодна, дети поняли, что воровать еду — это плохо, и решили заработать. Они отправились на ярмарку, чтобы показать фокусы. Джими был волшебником, который мог двигать предметы, но на самом деле невидимая Мейбл двигала их.\n\nНа ярмарке Джеральд представился мальчиком из Индии и собрал большую толпу, чтобы выступить. В конце концов Мейбл удалось снять кольцо, и Джеральд надел его, чтобы удивить публику, а затем они отправились домой. Но Мэйбл пришла в голову мысль вернуться домой, и они отправились в особняк вместе с невидимым Джеральдом. Тётя Мейбл очень обрадовалась, увидев девочку, и пообещала больше никогда на неё не сердиться.\n\nТем временем наступила ночь. Джеральд прогуливался по саду, когда увидел белую фигуру. Это было просто чудо, потому что фигурки в беседке, где постоянно сидели дети, оживали, это было сказочное место.\n\nЗатем Джеральд сделал своё дело, закрыл дверь в сокровищницу, повесил ключ и приготовился уходить. Но потом ему, как и любому человеку, захотелось есть, и он стал искать кухню. Но в одной из комнат он обнаружил грабителей. Он пытался помочь, но они украли много серебра.\n\nРанним утром Джеральд вернулся домой усталый и замёрзший. Экономка ругалась из-за грязных простыней, кольцо упало с пальца Джеральда, и он стал виден, но кольцо было потеряно. Потом дети собрались и с изумлением слушали Джеральда, потому что он рассказывал ночную сказку про разбойников и серебро, а потом он решил помочь Джонсону, это тот человек, который работает в этом замке, особняке, ну, он хотел рассказать, куда делись разбойники. Я забыл сказать тебе, что с детьми и Джонсоном был полицейский.\n\nОни вернулись в детский дом и поужинали, а потом все принялись искать кольцо, и Мейбл обвинила их горничную в краже кольца. и это правда, горничная Лиз действительно надела кольцо и стала невидимой, она пошла встречать своего жениха, а он был просто в шоке, он думал, что заболел или сошел с ума. Лиз была очень расстроена, она плакала и не знала, что делать, дети пошли в беседку на пикник с Лиз.\n\nНаступил вечер, и служанка Лиз заметила, что статуи движутся. Вот что происходит, когда вы надеваете Волшебное кольцо-невидимку. Она дотронулась до статуэтки и очень испугалась, в результате все-таки сняла кольцо и пообещала больше никогда не носить чужие украшения.\n\nПотом они купили газету, в которой было написано имя Джонсона и его подвиги с грабителями. Потом ребята пошли на рынок и купили цветы для Мадмазель, они пришли домой и подарили ей цветы. Мадмазель начала приглашать Мейбл в замок, и та рассказала ей всю историю. Муадмозелю очень понравилась Мейбл, и она решила устроить небольшой праздничный ужин. Она купила много вкусных вещей, и дети устроили для нее представление. Это очень длинная история со спектаклем, очень длинная, и в конце спектакля все чучела животных ожили. Это все из-за кольца, оно стало странным.\n\nМуадмозель в панике выбежал из дома. Они успокоили муадмозеля и подумали о том, что делать с пугалами, как убрать колдовство. Мейбл и Джеральд отнесли мягкие игрушки в беседку и стали гадать, когда же кончится это волшебство. Кстати, эти пугала были очень воспитаны, разговаривали как настоящие джентльмены, читать было очень смешно. Тогда лесник увидел все это, запер чучела и попросил Джеральда рассказать ему, что случилось.\n\nОни рассказали Леснику всю историю с кольцом и договорились встретиться на следующий день в 10, но Лесник открыл дверь раньше, и мягкие игрушки ранили его. Дети нашли дровосека и помогли ему, но одно чучело все еще было живо. Они придумали план, как заманить его и снять с него пальто, но случилось ужасное. Джимми буквально рос у них на глазах, и в конце концов он стал похож на сорокалетнего старика. Дети плакали и не знали, что делать. в результате им удалось снять заклятие, и они решили спрятать кольцо в замке и не трогать его."
}