{
    "title": "Несчастный случай",
    "author": "Зощенко",
    "annotation": "рассказа\nМикропересказ\n:\n \nМуж вместо валерианки по ошибке даёт жене большую дозу капель от ревматизма.\n\n\nЭтот микропересказ слишком короткий: 76 зн. Оптимальный размер: 190—200 знаков.\n\n\n\n\nЯ чуть не уморил свою супругу.\n\nОна у меня нервная. Без капель не может прожить. Если хотя бы чуть-чуть расстроится, то кáпаю валерианку. В следующий раз для того, чтобы побыстрее успокоить её, кáпаю капель пятьдесят, бывает все семьдесят. Недавно говорит, что надо ещё капель купить. Я купил пузырек без капельницы. Супруга начала возмущаться. Говорит, что без неё можно человека на тот свет отправить.\n\nБеда заключалась в том, что я по ошибке схватил другой пузырек — с каплями против суставного ревматизма. Налил капель шестьдесят. Выпила супруга эту порцию, и глаза у ней полезли на лоб. Была она спокойна целую неделю. Только все время пить хотела. А потом — ничего.\n\nТолько почему эти пузырьки делают без капельниц? Так ведь человека испортить можно.",
    "categories": [
        "Зощенко, Михаил Михайлович",
        "Рассказы",
        "Все пересказы по алфавиту",
        "Слишком короткие микропересказы"
    ],
    "source_file": "c1f91dd4cadfefa5cc8283bd6acb7f0fc88207b9cf0b1400f324afa1e7a1763e.raw"
}