{
    "title": "Отец наших душ",
    "author": "Абрамов",
    "annotation": "книги\nМикропересказ\n:\n \nЗаметки о личности и творчестве Пушкина.\n\n\nЭтот микропересказ слишком короткий: 40 зн. Оптимальный размер: 190—200 знаков.\n\n\n\n\nПушкин принимал всё истинно человеческое. Ему чужд был дух какого-либо сектантства. Он не любил лишь косность. И нам завещал любовь и ненависть — это тоже важнейший завет и урок Пушкина.\n\nВ произведениях Пушкина объединились разные жанры русской литературы — поэзия и проза, в наши дни противопоставляемые. Две сестры — две стороны литературы. Пушкин — душа и ум России. По Пушкину мы делаемся русскими, сынами и гражданами своего Отечества.\n\nЭтой всеобъединяющей силой не обладал и не обладает ни один писатель. А потому место Пушкина в нашем сердце, в нашей душе исключительное. Гений — это нация в одном человеке. И таким человеком был Пушкин, самый удивительный, самый гениальный человек, который рождался на Руси. В нём впервые в нашей литературе воссоединились два потока: интеллигенция и народ.\n\nПушкин велик не только своими произведениями, которые закончили формирование русского национального характера. Он задал направление всей русской поэзии, сердцевиной которого является государственность или иными словами патриотизм в высшей форме его проявления. И этого направления придерживались все великие поэты вплоть до Твардовского.\n\n«За далью — даль» по своему пафосу очень близка к «Медному всаднику» с его прославлением дел Петра. Не говоря о том, что Пушкин — создатель современного литературного языка, что от него пошла вся современная литература, он, наряду с матерью, первый воспитатель каждого человека, начиная с детства.\n\nГлазами Пушкина мы смотрим на мир, по-пушкински чувствуем, по-пушкински мы думаем. Пушкин — отец наших душ. Влияние Пушкина возрастает с каждым последующим поколением.\n\nПушкин остался в сознании всех как благороднейший человек, хотя и не без слабостей, джентльмен и рыцарь в любви, с чувством большого человеческого достоинства, чести, гордости и человечности. Не случайно Гоголь считал Пушкина человеком будущего.",
    "categories": [
        "Абрамов, Фёдор Александрович",
        "Все пересказы по алфавиту",
        "Нонфикшен",
        "Не указан жанр",
        "Слишком короткие микропересказы"
    ],
    "source_file": "b5580ffefa5ca4ce0bca07b8b3a31f19bcf559d08cf9083146e58d2bfb7a855b.raw"
}