{
    "title": "Принят",
    "author": "Шолом-Алейхем",
    "annotation": "рассказа\nиз цикла «\nЖелезнодорожные рассказы\n»\nМикропересказ\n:\n \nЕдущие в поезде пассажиры переживают, что их детей не принимают в гимназию.\n\n\nЭтот микропересказ слишком короткий: 75 зн. Оптимальный размер: 190—200 знаков.\n\n\n\n\nЕдущие в поезде пассажиры из разных местечек говорят о том, что их детей или не принимают вообще или принимают всего несколько человек. В разговор вступает пассажир из Перещепина и очень удивляется, что евреев не принимают, — детей в Перещепине приняли. Пассажиры не знают, что это за город Перещепин. Им объясняют, что есть два Перещепина, Большой Перещепин и Малый Перещепин. Так пассажир из Малого Перещепина.\n\nПассажиры набрасываются с вопросами на человека из Малого Перещепина. Неужели он не смеётся, и детей принимают без взяток? И что же это за гимназия в Малом Перещепине? Пассажир недоумевает: какая гимназия? Его сына приняли в солдаты.",
    "categories": [
        "Шолом-Алейхем",
        "Рассказы",
        "Все пересказы по алфавиту",
        "Не указан год публикации",
        "Слишком короткие микропересказы"
    ],
    "source_file": "fcf020e837a707cb8abe3aee1e5685254d62888e7e1c9b2e9acd2a950c560455.raw"
}