{
    "title": "Предвестник весны",
    "author": "Генри",
    "annotation": "рассказа\nиз цикла «\nГолос большого города\n»\nДля этого пересказа надо написать \nмикропересказ\n в 190—200 знаков.\n\n\n\n\nПриближается весна. Об этом говорит наше сердце, когда Дафнис начинает искать свою Хлою.\n\nМистер Питерс, мистер Рэгздейл и мистер Кид сидят в сквере на скамейке. У мистера Питерса, единственного из компании, есть жена. У неё в кармане — доллар, на который компания имеет виды. Питерс отвергает виды насилия, которые предлагают друзья, чтоб забрать доллар.\n\nПитерсы снимают комнату, такую тёмную, что хозяин краснеет, беря за неё плату. Миссис Питерс, женщина, весящая двести фунтов, иногда ходит убирать и стирать другим людям, мистер Питерс презирает такие занятия, так как вообще не работает.\n\nНи на какие уговоры миссис Питерс не поддаётся и доллар не отдаёт. Тогда мистер Питерс признаётся ей в любви. Увидев, что у мужа усталый вид и он исхудал, расплакавшаяся женщина выбегает из комнаты. Мистер Питерс упивается победой и недоумевает, куда убежала жена. Миссис Питерс возвращается с бутылкой сарсапариллы. Как хорошо, что у неё был этот доллар! Усевшись мужу на колени, она просит признаться ей любви ещё раз.\n\nВесна наступила. Друзья ждали мистера Питерса с долларом, а он жалел, что не прибегнул к насилию.",
    "categories": [
        "О. Генри",
        "Рассказы",
        "Все пересказы по алфавиту",
        "Нет микропересказа"
    ],
    "source_file": "508582a28821b6b68d1cc8c93bc6834fbcad1980017d37d768aa51b854915071.raw"
}