{
    "title": "Рассказ об Икриме и Хузейме",
    "author": "",
    "annotation": "сказки\nиз цикла «\nТысяча и одна ночь\n»\nДля этого пересказа надо написать \nмикропересказ\n в 190—200 знаков.\n\n\n\n\nНекий человек по имени Хузейма много помогал людям. Со временем он тоже стал нуждаться в помощи и люди помогли ему, но вскоре он им надоел. Хузейма закрылся в своём доме и стал ждать смерти.\n\nУзнав об этом, наместник Джазиры, Икрима, тайно пришёл к нему и принёс деньги. Жена Икримы решила, что её муж был у другой женщины, но муж рассказал ей правду.\n\nХузейма пришёл к халифу Сулейману и рассказал, что ему незнакомец оставил деньги. Сулейман назначил Хузейма наместником Джазиры вместо Икрима. Хузейма потребовал у Икрима отчёт и, видя недостачу, отправил Икрима в тюрьму.\n\nХузейм потребовал от Икрима, чтобы тот заплатил, но Икрим оказался.\n\n\n\n\n\nЯ не из тех, кто охраняет деньги ценой своей чести: делай что хочешь.\n\n\n\n\n\nЖена Икрима встретилась с Хузеймой и рассказала, кто его спас. Хузейма освободил больного Икрима из тюрьмы, хотел разделить с ним наказание, но Икрим отказался.\n\nХузейма привёл Икрима к Сулейману и они оба стали наместниками.\n\nЗа основу пересказа взято следующее издание сказки (Палек; Художественная литература, 1959)",
    "categories": [
        "Пересказы без карточек персонажей",
        "Сказки",
        "Все пересказы по алфавиту",
        "Тысяча и одна ночь",
        "Не указан автор",
        "Не указан год публикации",
        "Нет микропересказа"
    ],
    "source_file": "f9dc046c4ca343e7e46e970a3876a3c9712eba042e4f31ba26c7ad683bb10804.raw"
}