{
    "title": "С Земли на Луну",
    "author": "Верн",
    "annotation": "романа\nДля этого пересказа надо написать \nмикропересказ\n в 190—200 знаков.\n\n\n\n\nСобытия романа происходят сразу после гражданской войны в США, то есть очевидно в 1865—1866 годах. После окончания войны в Балтиморе (США) организован Пушечный клуб. Его основатель Импи Барбикен загорелся идеей создать пушку, снаряд которой мог бы после выстрела достигнуть Луны. Предварительные расчеты показали, что технология того времени вполне позволяла построить такое орудие. Барбикену удается привлечь внимание всего мира и собрать около 5,5 млн долларов на масштабный проект, спонсорами которого выступили многие страны, в том числе и США. Разработка исполинской пушки Колумбиады началась. Поскольку отлить такой ствол не представлялось возможным, в его качестве создатели решили использовать шахту в земле глубиной 900 футов (274 метра) с чугунными стенками диаметром 60 футов (18.3 метра), Вторую космическую скорость снаряду должен был придать заряд пироксилина общим весом 400 тысяч фунтов (180 тонн).\n\nПервоначально планировалось, что необитаемый шарообразный снаряд из сплава алюминия, достигнув поверхности Луны, мог привлечь внимание её возможных обитателей. Однако далее планы основателей проекта «Колумбиада» изменились. Французский путешественник Мишель Ардан предложил в качестве снаряда пушки изготовить полый металлический цилиндр, заостренный с одной стороны, и сам вызвался полететь внутри него. В итоге было принято решение подготовить вагон-снаряд для команды из 3 человек.\n\nПервыми космическими путешественниками стали: Капитан Николь — американец; Импи Барбикен — американец и Мишель Ардан — француз.\n\nВыстрел произошёл согласно намеченному плану и вагон-снаряд, унося первых космонавтов, отправился к Луне.",
    "categories": [
        "Нарушение авторских прав",
        "Верн, Жюль",
        "Романы",
        "Все пересказы по алфавиту",
        "Нет микропересказа"
    ],
    "source_file": "fd58ade481d6fc142b9afebc71432ffd6ccc7d5535fb71070e6143f9210e7348.raw"
}