{
    "title": "Труды и дни",
    "author": "Гесиод",
    "annotation": "поэмы\nМикропересказ\n:\n \nПоэт, взывая к музам, обратился к своему разорившемуся брату с наставлениями о личных отношениях, выборе жены, земледелии и ведении хозяйства. При этом он привёл мифологические сюжеты, басню и притчи.\n\n\n\n\nГесиод начал поэму с просьбы к музам, чтобы они воспели всемогущего Зевса. После этого он обратился к своему брату, обещая говорить только правду.\n\nГесиод указал на то, что существуют две разные богини Эриды: одна вызывает войны и вражду, другая же полезна для людей, потому что пробуждает дух соревнования. Поэт посоветовал брату избегать первую из них.\n\nГесиод плавно перешёл к рассказу мифа о Прометее. Боги скрыли от людей источники пищи, поэтому людям приходится постоянно работать. Зевс был в гневе из-за обмана Прометея, укравшего огонь для людей, и послал людям созданную богами девушку Пандору с сосудом, наполненным бедами и болезнями.\n\nДалее Гесиод перешёл к описанию смены веков. Первым было золотое поколение людей, когда все жили, не зная горя, трудов и не старея. Второе поколение — серебряное: эти гордые люди проходили путь от детства до старости, жили меньше и несчастнее, чем люди золотого поколения. Третье поколение — медное. Это были воинственные люди, могучие и страшные, их доспехи и дома были медными. Четвертое поколение героев было справедливее и лучше прежнего. О пятом поколении Гесиод сказал с сожалением: «Если бы мог я не жить с поко­ле­ни­ем пято­го века!». В это время землю населяли железные люди, страдающие от труда и горя. Люди этого поколения не могли договориться между собой, не имени совести и стыда.\n\nПосле описания поколений Гесиод привёл басню о соловье и ястребе. Ястреб, поймав соловья, сказал ему, что он может делать с ним всё, что захочет, потому что он сильнее. Тут Гесиод снова обратился к брату с советом избегать гордости, которая губительна «для малых людей и тем, кто повыше».\n\nГесиод описал два города: первый чтит правду и процветает, второй же, неправедный, пребывает в голоде и чуме. Богиня Дика следила за людьми и их поведением, а после рассказывала Зевсу о нарушениях. Гесиод снова напомнил брату следовать только голосу правды и забыть о насилии. Поэт также дал брату наставления о честном труде и предусмотрительности.\n\n\n\n\n\nТот — наи­луч­ший меж все­ми, кто вся­кое дело спо­со­бен\nСам обсудить и заране пред­видит, что вый­дет из дела.\n\n\n\n\n\nГесиод дал брату множество советов о том, как общаться с соседями, как брать и давать взаймы. Гесиод считал, что главное — работать, не откладывая дел, иначе придётся побираться. Он научил брата, в какое время нужно приниматься за посев, как и когда пахать землю. Гесиод предупредил брата, что зимнее время — самое опасное и для людей, и для животных. Не забыл поэт сказать и о сборе урожая, посоветовав вставать, как можно раньше. Он упомянул, в какое время собирать виноград, и посоветовал на десятый день после сбора сливать вино в бочки.\n\nНа случай, если брат захочет плавать по морю, Гесиод рассказал, в какое время лучше выходить в море, и посоветовал не оставлять корабль на воде, когда море бушует.\n\nГоворя о том, что всё нужно делать вовремя, Гесиод упомянул, что и жену в дом нужно брать, достигнув тридцати лет. Закончил Гесиод поэму разными мелкими, в том числе бытовыми, наставлениями и перечислением пригодных и непригодных дней для исполнения всяческих дел, вплоть до зачатия ребёнка.\n\nЗа основу пересказа взят \nперевод В. В. Вересаева\n из сборника «Эллин­ские поэты» (М.: Ладомир, 1999).",
    "categories": [
        "Гесиод",
        "Поэмы",
        "Все пересказы по алфавиту"
    ],
    "source_file": "c598c19bd99d08d8b590b3f8e25373380e8c94b4a7d638545dedbd3bfd5eedcf.raw"
}