{
    "title": "Фиалки по средам",
    "author": "Моруа",
    "annotation": "новеллы\nМикропересказ\n:\n \nВлюблённый в знаменитую актрису студент по средам посылает ей букетик фиалок. После его гибели актриса приносит букетик фиалок на его могилу.\n\n\nЭтот микропересказ слишком короткий: 141 зн. Оптимальный размер: 190—200 знаков.\n\n\n\n\nЖенни Сорбье окончила консерваторию с первой премией и сразу же была приглашена в знаменитый театр Комедии Францез. Благодаря таланту актрисы, блестящему образованию, обаянию и чудесным волосам она очень скоро стала одной из ведущих актрис театра.\n\nОднажды после спектакля, в среду, капельдинер передал ей букетик фиалок за два су. Швейцар сказал, что цветы принёс какой-то студент Политехнической школы в чёрном мундире. Студент приносил букетики фиалок каждую среду, когда у студентов Политехнической школы нет занятий. Так продолжалось полгода. В очередную среду Женни решила познакомиться со своим поклонником в антракте спектакля, но он не пришёл. И в следующую среду не было ни студента, ни фиалок. Женни с театром уехала на гастроли, которые прошли с большим успехом.\n\nСпустя год она приняла полковника Женеврьера по его просьбе. Он пришел, одетый в чёрный штатский костюм. Полковник сказал, что носит траур по сыну Андре, лейтенанту, убитому на Мадагаскаре два месяца назад. Это был тот самый студент, который каждую среду приносил букетик фиалок. Он боготворил Женни. Полковник передал ей целую пачку писем, которые так и не были отправлены.\n\nСразу после окончания Политехнической школы Андре попросил направить его на Мадагаскар. Сестре он сказал, что или разлука излечит его от безнадёжной страсти, или он совершит какой-нибудь подвиг и тогда...\n\nКаждую среду Женни идёт на кладбище Монпарнас и приносит букетик фиалок на могилу незнакомого ей лейтенанта.",
    "categories": [
        "Андре Моруа",
        "Новеллы",
        "Все пересказы по алфавиту",
        "Слишком короткие микропересказы"
    ],
    "source_file": "61deed4db625f7e8d24ed824ecad3989c826faad2ad129828f3bfa4fb9271ef8.raw"
}