{
    "title": "Черепаха",
    "author": "Пиранделло",
    "annotation": "рассказа\nМикропересказ\n:\n \nПриятель дарит герою черепаху, веря, что она приносит счастье. Дети героя относятся к ней жестоко, жена находит в ней повод для развода, а сам герой понимает, что хочет быть самим собой.\n\n\nЭтот микропересказ слишком короткий: 186 зн. Оптимальный размер: 190—200 знаков.\n\n\n\n\nПриятель мистера Мишкоу считает, что черепахи приносят счастье. Он играет на нью-йоркской бирже и каждое утро ставит свою черепаху перед лесенкой. Если животное пытается подняться по лесенке – акции поднимутся в цене, если черепаха отворачивается – цена акций упадёт, если же она втягивает голову и лапки под панцирь – цена не изменится. Именно поэтому приятель дарит мистеру Мишкоу маленькую черепаху.\n\nМистер Мишкоу, «подвижный кругленький человечек», несёт черепаху домой, дрожа от лёгкого отвращения и сознания, что похожий на камень предмет в его руке – живое существо. Дома он показывает черепаху дочери Элен и сыну Джону, но те не в восторге. Их глаза, по сравнению с живыми глазами отца, кажутся старческими, они смотрят на животное тяжёлым, свинцовым взглядом и не понимают, зачем отец принёс его в их красивый, чистый дом.\n\nМистер Мишкоу пытается объяснить детям, что с черепахой можно поиграть, и даже пытается показать, как это сделать – становится на четвереньки и подталкивает черепаху сзади, побуждая её выпустить лапки из-под панциря. Неожиданно Джон носком ботинка переворачивает животное на спинку, а Элен начинает хохотать, глядя, как оно пытается перевернуться. Мистер Микшоу понимает, что дети смогут обращаться с черепахой, только как «с самой жалкой игрушкой», и это ему не нравится.\n\nМистер Микшоу совсем не знает жизни. Раздевшись в ванной, он вполне способен удивиться своему собственному 42-летнему телу и задуматься, как для него «оказалась возможной самая сокровенная близость с такой непроницаемой женщиной, как миссис Мишкоу».\n\n\n\n\n\nДовольно-таки мучительно и даже немного страшно, что нет возможности объяснить себе, почему тело твоё неизбежно должно быть таким, какое оно есть, не каким-нибудь другим, совершенно иным.\n\n\n\n\n\nЖенатый уже девять лет, мистер Мишкоу до сих пор не понимает, как он оказался супругом миссис Мишкоу, красивой, как покрытая глазурью фарфоровая статуэтка. Она настолько отрешена и изолирована ото всех, что непонятно, как такая женщина стала женой мужчины из плоти и крови. Зато понятно, почему из этого фарфорового лона вышли «такие высохшие на корню детки» – они состарились ещё до своего рождения.\n\nВозможно, они родились бы другими, выноси их сам мистер Микшоу, но он даже о беременностях жены ничего не знал. Она просто отправлялась на полтора месяца в клинику и возвращалась с ребёнком-старичком. Мистер Мишкоу даже не был до конца уверен, что детей родила его жена.\n\nВсе девять лет брака мистер Мишкоу боялся, что жена найдёт повод для развода. Вернувшись домой и застав мужа на четвереньках перед черепахой, миссис Мишкоу предоставляет ему выбор: либо он избавляется от мерзкого животного, либо она уезжает к матери в Англию. Не желая потерять жену, мистер Мишкоу берёт черепаху и отправляется к магазину, где она была куплена.\n\nОбнаружив, что в огромном, фантасмагорическом, похожем на колоссальные, но временные декорации городе наступил вечер и магазин уже закрыт, мистер Мишкоу садится в такси, намереваясь оставить черепаху в машине.\n\n\n\n\n\nЖалко, что у этой зверюшки, всё ещё съёжившейся под своим щитком, по-видимому, так мало воображения. Интересно представить себе, как черепаха ночью разъезжает по всему Нью-Йорку.\n\n\n\n\n\nЗатем мистер Мишкоу решает, что поступать так с живым существом жестоко, выходит из такси и пытается оставить черепаху на цветочной клумбе. Его останавливает полицейский и велит убрать черепаху – это не положено. На уговоры полицейский не поддаётся, взять животное себе не хочет, и мистер Мишкоу снова остаётся с черепахой в руках.\n\nВнезапно он понимает, что для жены черепаха – только предлог, устранив его, она найдёт другой. Но ей трудно будет найти предлог, выглядящий ещё более нелепо в глазах судьи и общества, и мистеру Мишкоу глупо не воспользоваться этим.\n\nОн возвращается домой и кладёт черепаху на ковёр перед женой. Миссис Мишкоу немедленно уходит, а зверюшка внезапно оживает и начинает бодро ползать по гостиной. Глядя на черепаху, мистер Мишкоу неуверенно думает: «А счастье-то вот оно, счастье!».",
    "categories": [
        "Пиранделло, Луиджи",
        "Рассказы",
        "Все пересказы по алфавиту",
        "Слишком короткие микропересказы"
    ],
    "source_file": "459b7f97ff2a473ff399783b943a60e556acf61b95d3aa4e1b67d95bf2d7a998.raw"
}